.lc3py.mesonpy.libs/liblc3.so.1
.lc3py.mesonpy.libs/pkgconfig/lc3.pc
lc3py-1.1.2.data/headers/lc3.h
lc3py-1.1.2.data/headers/lc3_cpp.h
lc3py-1.1.2.data/headers/lc3_private.h
lc3py-1.1.2.data/purelib/lc3.py
lc3py-1.1.2.dist-info/METADATA
lc3py-1.1.2.dist-info/WHEEL
lc3py-1.1.2.dist-info/RECORD
