Metadata-Version: 2.1
Name: lc3py
Version: 1.1.2
Summary: LC3 Codec library wrapper
Author-Email: Antoine Soulier <asoulier@google.com>
License: Apache-2.0
Project-URL: Homepage, https://github.com/google/liblc3
Requires-Python: >=3.10
Provides-Extra: dev
Requires-Dist: pytest; extra == "dev"
